Metadata-Version: 2.1
Name: topsis-101983034
Version: 1.0.0
Summary: topsis
Home-page: https://github.com/SolarBoar808746/topsis_101983034
Author: Parshant Asija
Author-email: puru.asija19@gmail.com
License: MIT
Platform: UNKNOWN
Classifier: License :: OSI Approved :: MIT License
Classifier: Programming Language :: Python :: 3.6
Classifier: Programming Language :: Python :: 3.7
Classifier: Programming Language :: Python :: 3.8
